pyxmas/__init__.py
pyxmas/__main__.py
pyxmas/_logging.py
pyxmas-0.2.1.dist-info/LICENSE
pyxmas-0.2.1.dist-info/METADATA
pyxmas-0.2.1.dist-info/WHEEL
pyxmas-0.2.1.dist-info/top_level.txt
pyxmas-0.2.1.dist-info/RECORD
