Metadata-Version: 2.1
Name: pyxmas
Version: 0.2.1
Summary: Explainable multi-agent systems in Python
Home-page: https://github.com/pikalab-unibo/pyxmas
Author: Giovanni Ciatto
Author-email: giovanni.ciatto@unibo.it
License: Apache 2.0 License
Project-URL: Bug Reports, https://github.com/pikalab-unibo/pyxmas/issues
Project-URL: Source, https://github.com/pikalab-unibo/pyxmas
Keywords: expectation,chistera,xai,mas
Platform: Independant
Classifier: Development Status :: 3 - Alpha
Classifier: Intended Audience :: Developers
Classifier: Topic :: Software Development :: Libraries
Classifier: Topic :: Scientific/Engineering :: Artificial Intelligence
Classifier: License :: OSI Approved :: Apache Software License
Classifier: Programming Language :: Python :: 3
Classifier: Programming Language :: Python :: 3.9
Classifier: Programming Language :: Python :: 3 :: Only
Requires-Python: >=3.9.0
License-File: LICENSE
Requires-Dist: spade (==3.2.3)
